django_cache_decorator/__about__.py
django_cache_decorator/__init__.py
django_cache_decorator/py.typed
django_cache_decorator/utils.py
django3_cache_decorator-0.5.3.dist-info/METADATA
django3_cache_decorator-0.5.3.dist-info/WHEEL
django3_cache_decorator-0.5.3.dist-info/licenses/LICENSE.txt
django3_cache_decorator-0.5.3.dist-info/RECORD
