Metadata-Version: 2.3
Name: django3-cache-decorator
Version: 0.5.3
Project-URL: Documentation, https://github.com/Xiang Wang/django3-cache-decorator#readme
Project-URL: Issues, https://github.com/Xiang Wang/django3-cache-decorator/issues
Project-URL: Source, https://github.com/Xiang Wang/django3-cache-decorator
Author-email: Xiang Wang <ramwin@qq.com>
License: MIT
Classifier: Development Status :: 4 - Beta
Classifier: Programming Language :: Python
Classifier: Programming Language :: Python :: 3.8
Classifier: Programming Language :: Python :: 3.9
Classifier: Programming Language :: Python :: 3.10
Classifier: Programming Language :: Python :: 3.11
Classifier: Programming Language :: Python :: 3.12
Classifier: Programming Language :: Python :: Implementation :: CPython
Classifier: Programming Language :: Python :: Implementation :: PyPy
Requires-Python: >=3.8
